{"index":{"_id":"630","_index":"motorcycle_forum"}} 
{"Content":"The date is out, 19 May 2024. I will be riding the Audubon, New Jersey ride. Anyone else riding in NJ?\n\nThe Distinguished Gentleman's Ride\nSide By Side Worldwide. Register now for The 2024 Distinguished Gentleman’s Ride and join us on the 19th May 2024.\nwww.gentlemansride.com","Breadcrumbs":"Home\nForums\nMotorcycle Events\nNortheastern USA","Title":"Distinguished Gentleman's Ride 2024","Author":"Traveller11","URL":"https://www.motorcycleforum.com/threads/distinguished-gentlemans-ride-2024.253247/","Date":"2024-02-16","Tags":[]}
