[{
  "Content": "MV Agusta enter the hard-fought adventure market with new £21,800 triple cylinder Enduro Veloce\n\n\nMV Agusta introduce Enduro Veloce middleweight adventure bike\nSee details of all new middleweight Enduro Veloce from MV Agusta. Is the triple cylinder platform ready to tackle the ultra competitive adventure market?\nwww.motorcyclenews.com",
  "Breadcrumbs": "Home\nForums\nMotorcycle Related News\nMotorcycle News Articles",
  "Title": "MV Agusta Enters The Adventure Bike Field",
  "Author": "Steadfastly",
  "URL": "https://www.motorcycleforum.com/threads/mv-agusta-enters-the-adventure-bike-field.253616/",
  "Date": "Apr 8, 2024",
  "Tags": []
}]