[{
  "Content": "These are pictures of my Dad's motorcycle which he rode in Germany mid to late 1950. He did not buy this new. I'm also not sure if it is a domestic German bike or an import. I would so love to know what kind of bike it is. Thank you so much for any help you can provide.",
  "Breadcrumbs": "Home\nForums\n🏍 Motorcycle Forums 🏍\nVintage Forum",
  "Title": "Need Help Identifying this Bike...",
  "Author": "heidigraw",
  "URL": "https://www.motorcycleforum.com/threads/need-help-identifying-this-bike.253308/",
  "Date": "Feb 27, 2024",
  "Tags": []
}]